scope_analytics/__init__.py
scope_analytics/auto.py
scope_analytics/cli.py
scope_analytics/client.py
scope_analytics/config.py
scope_analytics/context.py
scope_analytics/events.py
scope_analytics/middleware.py
scope_analytics/queue.py
scope_analytics/patches/__init__.py
scope_analytics/patches/anthropic_patch.py
scope_analytics/patches/gemini_patch.py
scope_analytics/patches/openai_patch.py
scope_analytics-0.1.1.dist-info/licenses/LICENSE
scope_analytics-0.1.1.dist-info/METADATA
scope_analytics-0.1.1.dist-info/WHEEL
scope_analytics-0.1.1.dist-info/entry_points.txt
scope_analytics-0.1.1.dist-info/top_level.txt
scope_analytics-0.1.1.dist-info/RECORD
